tencentcloud/__init__.py
tencentcloud/vm/__init__.py
tencentcloud/vm/v20200709/__init__.py
tencentcloud/vm/v20200709/errorcodes.py
tencentcloud/vm/v20200709/models.py
tencentcloud/vm/v20200709/vm_client.py
tencentcloud/vm/v20200709/vm_client_async.py
tencentcloud/vm/v20201229/__init__.py
tencentcloud/vm/v20201229/errorcodes.py
tencentcloud/vm/v20201229/models.py
tencentcloud/vm/v20201229/vm_client.py
tencentcloud/vm/v20201229/vm_client_async.py
tencentcloud/vm/v20210922/__init__.py
tencentcloud/vm/v20210922/errorcodes.py
tencentcloud/vm/v20210922/models.py
tencentcloud/vm/v20210922/vm_client.py
tencentcloud/vm/v20210922/vm_client_async.py
tencentcloud_sdk_python_vm-3.1.19.dist-info/METADATA
tencentcloud_sdk_python_vm-3.1.19.dist-info/WHEEL
tencentcloud_sdk_python_vm-3.1.19.dist-info/top_level.txt
tencentcloud_sdk_python_vm-3.1.19.dist-info/RECORD
